historydag/__init__.py
historydag/_version.py
historydag/beast_loader.py
historydag/compact_genome.py
historydag/counterops.py
historydag/dag.py
historydag/dag_node.py
historydag/dag_pb2.py
historydag/likelihoods.py
historydag/mutation_annotated_dag.py
historydag/parsimony.py
historydag/parsimony_utils.py
historydag/sankoff_cli.py
historydag/sequence_dag.py
historydag/utils.py
historydag-1.3.0.dist-info/LICENSE
historydag-1.3.0.dist-info/METADATA
historydag-1.3.0.dist-info/WHEEL
historydag-1.3.0.dist-info/top_level.txt
historydag-1.3.0.dist-info/RECORD
