Metadata-Version: 2.1
Name: historydag
Version: 1.3.0
Summary: Basic history DAG implementation
Home-page: https://matsengrp.github.io/historydag
Author: Will Dumm
Author-email: wdumm88@gmail.com
Classifier: Programming Language :: Python :: 3
Classifier: License :: OSI Approved :: GNU General Public License (GPL)
Classifier: Operating System :: OS Independent
Requires-Python: >=3.7
License-File: LICENSE
Requires-Dist: six
Requires-Dist: PyQt5
Requires-Dist: ete3
Requires-Dist: biopython
Requires-Dist: graphviz
Requires-Dist: frozendict
Requires-Dist: protobuf
